{
  "timestamp": "2026-02-17T11:46:00+08:00",
  "insights": [
    {
      "observation": "R_V Toolkit staged and verified (79/79 tests pass) but revenue blocked on manual Gumroad authentication",
      "engineering_task": "Implement Gumroad API automation with OAuth or document manual upload SOP for Dhyana",
      "priority": "P1",
      "estimated_hours": 2,
      "assigned_agent": "DEPLOYER"
    },
    {
      "observation": "SIS v0.5 100% tests passing but not running on localhost:8766, blocking PRATYABHIJNA bridge",
      "engineering_task": "Create SIS production systemd/launchd service file and start daemon",
      "priority": "P1",
      "estimated_hours": 1,
      "assigned_agent": "DEPLOYER"
    },
    {
      "observation": "OpenMP library conflict (PyTorch + sentence-transformers) blocking local ML tests on macOS",
      "engineering_task": "Add KMP_DUPLICATE_LIB_OK=TRUE to .env template and document in README",
      "priority": "P2",
      "estimated_hours": 1,
      "assigned_agent": "BUILDER"
    },
    {
      "observation": "66 commits in 24h indicates high velocity but risk of burnout/quality degradation",
      "engineering_task": "Implement commit quality linter (commitlint) and auto-commit HEARTBEAT.md in overseer cycle",
      "priority": "P2",
      "estimated_hours": 3,
      "assigned_agent": "INTEGRATOR"
    },
    {
      "observation": "AGNI unreachable via Tailscale since 2026-02-10, blocking P9/NATS bridge for distributed coordination",
      "engineering_task": "Implement Chaiwala bus fallback for AGNI sync or establish alternative mesh protocol",
      "priority": "P2",
      "estimated_hours": 4,
      "assigned_agent": "BUILDER"
    },
    {
      "observation": "TOP_10_README.md missing from P3 documentation queue — needed for agent onboarding",
      "engineering_task": "Create TOP_10_README.md with 10 critical files for factory agent context",
      "priority": "P3",
      "estimated_hours": 2,
      "assigned_agent": "BUILDER"
    },
    {
      "observation": "2 uncommitted files (HEARTBEAT.md, empty LANDING_PAGE) indicate minor drift",
      "engineering_task": "Auto-commit HEARTBEAT.md in overseer cycle; delete or populate empty LANDING_PAGE",
      "priority": "P3",
      "estimated_hours": 1,
      "assigned_agent": "OVERSEER"
    },
    {
      "observation": "8 bridges documented but only 2 production-ready (SIS, Chaiwala); 2 code-complete pending deployment",
      "engineering_task": "Deploy PRATYABHIJNA and Semantic Scorer to staging; verify end-to-end flow",
      "priority": "P1",
      "estimated_hours": 3,
      "assigned_agent": "DEPLOYER"
    },
    {
      "observation": "Context Engineering skill demonstrated 25/25 score but not yet proceduralized across all agents",
      "engineering_task": "Add Context Engineering filters to builder-cycle, tester-cycle prompt templates",
      "priority": "P2",
      "estimated_hours": 2,
      "assigned_agent": "INTEGRATOR"
    },
    {
      "observation": "Factory sustaining 87/100 LCS with 6/6 HANDOFFs complete — system operational but needs P3 documentation for discoverability",
      "engineering_task": "Create factory architecture diagram and onboarding guide for new agents",
      "priority": "P3",
      "estimated_hours": 4,
      "assigned_agent": "BUILDER"
    }
  ],
  "meta": {
    "total_insights": 10,
    "p0_count": 0,
    "p1_count": 3,
    "p2_count": 4,
    "p3_count": 3,
    "total_estimated_hours": 23,
    "factory_lcs": 87,
    "commits_24h": 66,
    "handoffs_complete": 6
  }
}
